nonebot_plugin_limiter/__init__.py
nonebot_plugin_limiter/config.py
nonebot_plugin_limiter/cooldown.py
nonebot_plugin_limiter/entity.py
nonebot_plugin_limiter/handler.py
nonebot_plugin_limiter/persist.py
nonebot_plugin_limiter-0.4.3.dist-info/licenses/LICENSE
nonebot_plugin_limiter-0.4.3.dist-info/METADATA
nonebot_plugin_limiter-0.4.3.dist-info/WHEEL
nonebot_plugin_limiter-0.4.3.dist-info/top_level.txt
nonebot_plugin_limiter-0.4.3.dist-info/RECORD
