Metadata-Version: 2.4
Name: nonebot-plugin-limiter
Version: 0.4.3
Summary: 通用消息冷却限制器
Author-email: MiddleRed <middlered@outlook.com>
Project-URL: Repository, https://github.com/owner/nonebot-plugin-limiter
Requires-Python: <4.0,>=3.10
License-File: LICENSE
Requires-Dist: nonebot2<3.0.0,>=2.4.2
Requires-Dist: nonebot-plugin-localstore<1.0.0,>=0.7.4
Requires-Dist: nonebot-plugin-apscheduler<1.0.0,>=0.5.0
Requires-Dist: nonebot-plugin-uninfo<1.0.0,>=0.7.3
Requires-Dist: nonebot-plugin-alconna<1.0.0,>=0.57.2
Requires-Dist: httpx<1.0.0,>=0.27.0
Requires-Dist: tzlocal>=3.0
Dynamic: license-file
